ffsize.py
ffsize-1.0.4.dist-info/LICENSE
ffsize-1.0.4.dist-info/METADATA
ffsize-1.0.4.dist-info/WHEEL
ffsize-1.0.4.dist-info/entry_points.txt
ffsize-1.0.4.dist-info/top_level.txt
ffsize-1.0.4.dist-info/RECORD
