Metadata-Version: 2.1
Name: ffsize
Version: 1.0.4
Summary: Counts all the files, folders, total sizes, and optionally crc in the directory recursively.
Home-page: https://github.com/elesiuta/ffsize
License: UNKNOWN
Platform: UNKNOWN
Classifier: Programming Language :: Python :: 3
Classifier: License :: OSI Approved :: MIT License
Classifier: Operating System :: OS Independent
Classifier: Topic :: Utilities
Classifier: Intended Audience :: End Users/Desktop
Classifier: Environment :: Console
Classifier: Development Status :: 5 - Production/Stable
